{"elapsed":"0.564","endpoint-url":"https://github.com/digital-land/design-code-collection/raw/main/data/Hyndburn/HNCHZBJU.zip","entry-date":"2022-12-16T00:12:25.680682","request-headers":{"Accept":"*/*","Accept-Encoding":"gzip, deflate","Connection":"keep-alive","User-Agent":"DLUHC Digital Land"},"resource":"08b656dcede0aa79c849634e34559a97041233b3f5ccc6ec9bf7d54b30a76f1f","response-headers":{"Accept-Ranges":"bytes","Access-Control-Allow-Origin":"*","Cache-Control":"max-age=300","Connection":"keep-alive","Content-Length":"4036","Content-Security-Policy":"default-src 'none'; style-src 'unsafe-inline'; sandbox","Content-Type":"application/zip","Date":"Fri, 16 Dec 2022 00:12:28 GMT","ETag":"W/\"7352f11b1daf9bc4e0cbf8aa8f64b072e9b836e45033b75fc935c57e9b458dbe\"","Expires":"Fri, 16 Dec 2022 00:17:28 GMT","Source-Age":"0","Strict-Transport-Security":"max-age=31536000","Vary":"Authorization,Accept-Encoding,Origin","Via":"1.1 varnish","X-Cache":"MISS","X-Cache-Hits":"0","X-Content-Type-Options":"nosniff","X-Fastly-Request-ID":"f5a7fc27b5ef8cdfa5b5ca28be6428b7d98f2a94","X-Frame-Options":"deny","X-GitHub-Request-Id":"2670:500B:226F95:348D68:639BB7EC","X-Served-By":"cache-sjc10042-SJC","X-Timer":"S1671149548.089371,VS0,VE240","X-XSS-Protection":"1; mode=block"},"ssl-verify":true,"status":"200"}