{"elapsed":"0.275","endpoint-url":"https://raw.githubusercontent.com/digital-land/design-code-collection/main/data/Buckinghamshire/Buckinghamshire_region.zip","entry-date":"2022-06-21T00:12:12.186395","request-headers":{"Accept":"*/*","Accept-Encoding":"gzip, deflate","Connection":"keep-alive","User-Agent":"DLUHC Digital Land"},"resource":"85e26113cbc3ced698aa72be161c968f0a63573a7593c43cab12e5431027d40c","response-headers":{"Accept-Ranges":"bytes","Access-Control-Allow-Origin":"*","Cache-Control":"max-age=300","Connection":"keep-alive","Content-Length":"117188","Content-Security-Policy":"default-src 'none'; style-src 'unsafe-inline'; sandbox","Content-Type":"application/zip","Date":"Tue, 21 Jun 2022 00:12:13 GMT","ETag":"W/\"71b49fd457c0944731c69ac0e4453b395f06def10997d281a1244985967a991e\"","Expires":"Tue, 21 Jun 2022 00:17:13 GMT","Source-Age":"0","Strict-Transport-Security":"max-age=31536000","Vary":"Authorization,Accept-Encoding,Origin","Via":"1.1 varnish","X-Cache":"MISS","X-Cache-Hits":"0","X-Content-Type-Options":"nosniff","X-Fastly-Request-ID":"c7df654c786d0cd8f7d6bb2eed6b4da198b6c6c5","X-Frame-Options":"deny","X-GitHub-Request-Id":"8EEE:3CDA:55B304:73570D:62B10CDD","X-Served-By":"cache-bur-kbur8200174-BUR","X-Timer":"S1655770333.257143,VS0,VE248","X-XSS-Protection":"1; mode=block"},"ssl-verify":true,"status":"200"}