{"elapsed":"0.287","endpoint-url":"https://github.com/digital-land/design-code-collection/raw/main/data/Hyndburn/HNCHZBJU.zip","entry-date":"2022-12-17T00:12:55.306358","request-headers":{"Accept":"*/*","Accept-Encoding":"gzip, deflate","Connection":"keep-alive","User-Agent":"DLUHC Digital Land"},"resource":"08b656dcede0aa79c849634e34559a97041233b3f5ccc6ec9bf7d54b30a76f1f","response-headers":{"Accept-Ranges":"bytes","Access-Control-Allow-Origin":"*","Cache-Control":"max-age=300","Connection":"keep-alive","Content-Length":"4036","Content-Security-Policy":"default-src 'none'; style-src 'unsafe-inline'; sandbox","Content-Type":"application/zip","Date":"Sat, 17 Dec 2022 00:12:56 GMT","ETag":"W/\"7352f11b1daf9bc4e0cbf8aa8f64b072e9b836e45033b75fc935c57e9b458dbe\"","Expires":"Sat, 17 Dec 2022 00:17:56 GMT","Source-Age":"0","Strict-Transport-Security":"max-age=31536000","Vary":"Authorization,Accept-Encoding,Origin","Via":"1.1 varnish","X-Cache":"MISS","X-Cache-Hits":"0","X-Content-Type-Options":"nosniff","X-Fastly-Request-ID":"f3505c5f7800f9ceb5c536d468c0328ffe9fd15b","X-Frame-Options":"deny","X-GitHub-Request-Id":"0E76:4FA5:6CD62F:96903A:639D0988","X-Served-By":"cache-iad-kiad7000063-IAD","X-Timer":"S1671235977.585636,VS0,VE83","X-XSS-Protection":"1; mode=block"},"ssl-verify":true,"status":"200"}