{"elapsed":"0.183","endpoint-url":"https://raw.githubusercontent.com/digital-land/design-code-collection/main/data/Portsmouth/design-code.csv","entry-date":"2023-12-12T00:13:20.162279","request-headers":{"Accept":"*/*","Accept-Encoding":"gzip, deflate","Connection":"keep-alive","User-Agent":"DLUHC Digital Land"},"resource":"b6bad35fa0dbeb01c0abd175de33dc972bda17527640485ccdaa399fb5656918","response-headers":{"Accept-Ranges":"bytes","Access-Control-Allow-Origin":"*","Cache-Control":"max-age=300","Connection":"keep-alive","Content-Encoding":"gzip","Content-Length":"307","Content-Security-Policy":"default-src 'none'; style-src 'unsafe-inline'; sandbox","Content-Type":"text/plain; charset=utf-8","Cross-Origin-Resource-Policy":"cross-origin","Date":"Tue, 12 Dec 2023 00:13:23 GMT","ETag":"W/\"83e264779d558204172739da1c63cc00e60379f3a987ca152bf2797c3d0e790d\"","Expires":"Tue, 12 Dec 2023 00:18:23 GMT","Source-Age":"0","Strict-Transport-Security":"max-age=31536000","Vary":"Authorization,Accept-Encoding,Origin","Via":"1.1 varnish","X-Cache":"MISS","X-Cache-Hits":"0","X-Content-Type-Options":"nosniff","X-Fastly-Request-ID":"11a4e98356949ef8e6b099ac8f89390fb590ad84","X-Frame-Options":"deny","X-GitHub-Request-Id":"0E90:2E54:13CE0D:18049B:6577A593","X-Served-By":"cache-bur-kbur8200100-BUR","X-Timer":"S1702340004.642888,VS0,VE173","X-XSS-Protection":"1; mode=block"},"ssl-verify":true,"status":"200"}