{"elapsed":"0.218","endpoint-url":"https://raw.githubusercontent.com/digital-land/design-code-collection/main/data/Buckinghamshire/Buckinghamshire_region.zip","entry-date":"2024-02-29T00:12:27.762580","request-headers":{"Accept":"*/*","Accept-Encoding":"gzip, deflate","Connection":"keep-alive","User-Agent":"DLUHC Digital Land"},"resource":"85e26113cbc3ced698aa72be161c968f0a63573a7593c43cab12e5431027d40c","response-headers":{"Accept-Ranges":"bytes","Access-Control-Allow-Origin":"*","Cache-Control":"max-age=300","Connection":"keep-alive","Content-Length":"117188","Content-Security-Policy":"default-src 'none'; style-src 'unsafe-inline'; sandbox","Content-Type":"application/zip","Cross-Origin-Resource-Policy":"cross-origin","Date":"Thu, 29 Feb 2024 00:12:28 GMT","ETag":"W/\"71b49fd457c0944731c69ac0e4453b395f06def10997d281a1244985967a991e\"","Expires":"Thu, 29 Feb 2024 00:17:28 GMT","Source-Age":"0","Strict-Transport-Security":"max-age=31536000","Vary":"Authorization,Accept-Encoding,Origin","Via":"1.1 varnish","X-Cache":"MISS","X-Cache-Hits":"0","X-Content-Type-Options":"nosniff","X-Fastly-Request-ID":"3c030256e100dc5b778293ba7c5c5c07fe1b9b0d","X-Frame-Options":"deny","X-GitHub-Request-Id":"1C06:3F0F:2B5E4C:343E79:65DFCBEB","X-Served-By":"cache-sjc1000143-SJC","X-Timer":"S1709165548.307913,VS0,VE202","X-XSS-Protection":"1; mode=block"},"ssl-verify":true,"status":"200"}